[
  {
    "id": "1337278",
    "nombre": "Bumthang Dzongkhag"
  },
  {
    "id": "1337279",
    "nombre": "Distrito de Chukha"
  },
  {
    "id": "1337280",
    "nombre": "Distrito de Dagana"
  },
  {
    "id": "1337286",
    "nombre": "Distrito de Paro"
  },
  {
    "id": "1337290",
    "nombre": "Distrito de Samdrup Jongkhar"
  },
  {
    "id": "7303651",
    "nombre": "Gasa"
  },
  {
    "id": "1337283",
    "nombre": "Haa Dzongkhag"
  },
  {
    "id": "1337284",
    "nombre": "Lhuentse Dzongkhag"
  },
  {
    "id": "1337285",
    "nombre": "Mongar Dzongkhag"
  },
  {
    "id": "1337287",
    "nombre": "Pemagatshel Dzongkhag"
  },
  {
    "id": "1337288",
    "nombre": "Punakha Dzongkhag"
  },
  {
    "id": "1337289",
    "nombre": "Samtse Dzongkhag"
  },
  {
    "id": "1337282",
    "nombre": "Sarpang Dzongkhag"
  },
  {
    "id": "1337293",
    "nombre": "Thimphu Dzongkhag"
  },
  {
    "id": "7303653",
    "nombre": "Trashi Yangste"
  },
  {
    "id": "1337292",
    "nombre": "Trashigang Dzongkhag"
  },
  {
    "id": "1337294",
    "nombre": "Trongsa Dzongkhag"
  },
  {
    "id": "1337281",
    "nombre": "Tsirang Dzongkhag"
  },
  {
    "id": "1337295",
    "nombre": "Wangdue Phodrang Dzongkhag"
  },
  {
    "id": "1337291",
    "nombre": "Zhemgang Dzongkhag"
  }
]