[
  {
    "id": "7280292",
    "nombre": "Choiseul"
  },
  {
    "id": "2108831",
    "nombre": "Guadalcanal"
  },
  {
    "id": "9259067",
    "nombre": "Honiara"
  },
  {
    "id": "2108262",
    "nombre": "Isabel"
  },
  {
    "id": "2178730",
    "nombre": "Makira"
  },
  {
    "id": "2106552",
    "nombre": "Malaita"
  },
  {
    "id": "2109495",
    "nombre": "Provincia Central"
  },
  {
    "id": "2101556",
    "nombre": "Provincia Occidental"
  },
  {
    "id": "7280293",
    "nombre": "Rennell y Bellona"
  },
  {
    "id": "2178472",
    "nombre": "Temotu"
  }
]